dreadlocks/__init__.py
dreadlocks/errors.py
dreadlocks/globals.py
dreadlocks/path_lock-test.py
dreadlocks/path_lock.py
dreadlocks/platform.py
dreadlocks/pool.py
dreadlocks/process.py
dreadlocks/process_level_lock.py
dreadlocks/process_level_path_lock.py
dreadlocks/thread.py
dreadlocks/thread_level_lock.py
dreadlocks/thread_level_path_lock.py
dreadlocks-0.0.15.dist-info/LICENSE
dreadlocks-0.0.15.dist-info/LICENSE.BSD-2-Clause
dreadlocks-0.0.15.dist-info/LICENSE.GPL-3.0-or-later
dreadlocks-0.0.15.dist-info/LICENSE.LGPL-3.0-or-later
dreadlocks-0.0.15.dist-info/METADATA
dreadlocks-0.0.15.dist-info/WHEEL
dreadlocks-0.0.15.dist-info/RECORD
