Metadata-Version: 2.1
Name: dreadlocks
Version: 0.0.15
Summary: A cross-platform cross-parallelization file-locking software library for Python.
License: BSD-2-Clause OR LGPL-3.0-or-later OR GPL-3.0-or-later
Author: Pid Zwei
Author-email: zweipid+dreadlocks@gmail.com
Requires-Python: >=3.9,<4.0
Classifier: License :: Other/Proprietary License
Classifier: Programming Language :: Python :: 3
Classifier: Programming Language :: Python :: 3.9
Classifier: Programming Language :: Python :: 3.10
Classifier: Programming Language :: Python :: 3.11
Classifier: Programming Language :: Python :: 3.12
